geoclip/__init__.py
geoclip/images/Kauai.png
geoclip/model/GeoCLIP.py
geoclip/model/__init__.py
geoclip/model/image_encoder.py
geoclip/model/location_encoder.py
geoclip/model/misc.py
geoclip/model/gps_gallery/coordinates_100K.csv
geoclip/model/rff/__init__.py
geoclip/model/rff/functional.py
geoclip/model/rff/layers.py
geoclip/model/weights/image_encoder_mlp_weights.pth
geoclip/model/weights/location_encoder_weights.pth
geoclip/model/weights/logit_scale_weights.pth
geoclip/train/__init__.py
geoclip/train/dataloader.py
geoclip/train/eval.py
geoclip/train/train.py
geoclip-1.2.0.dist-info/LICENSE
geoclip-1.2.0.dist-info/METADATA
geoclip-1.2.0.dist-info/WHEEL
geoclip-1.2.0.dist-info/top_level.txt
geoclip-1.2.0.dist-info/RECORD
