Metadata-Version: 2.1
Name: geoclip
Version: 1.2.0
Home-page: https://github.com/VicenteVivan/geo-clip
Author: Vicente Vivanco
Author-email: vicente.vivancocepeda@ucf.edu
License: MIT
Classifier: Programming Language :: Python :: 3
Classifier: License :: OSI Approved :: MIT License
Classifier: Operating System :: OS Independent
Requires-Python: >=3.6
License-File: LICENSE
Requires-Dist: torch
Requires-Dist: torchvision
Requires-Dist: Pillow
Requires-Dist: transformers
Requires-Dist: pandas
Requires-Dist: numpy
Requires-Dist: geopy
